hyls/__init__.py
hyls/__main__.py
hyls/jedhy.py
hyls/server.py
hy_language_server-0.0.6.dist-info/LICENSE
hy_language_server-0.0.6.dist-info/METADATA
hy_language_server-0.0.6.dist-info/WHEEL
hy_language_server-0.0.6.dist-info/entry_points.txt
hy_language_server-0.0.6.dist-info/top_level.txt
hy_language_server-0.0.6.dist-info/RECORD
