Metadata-Version: 2.1
Name: hy-language-server
Version: 0.0.6
Summary: hy language server using Jedhy
Home-page: https://github.com/rinx/hy-language-server
Author: Rintaro Okamura
Author-email: rintaro.okamura@gmail.com
License: UNKNOWN
Platform: UNKNOWN
Requires-Python: >=3.6
Requires-Dist: argparse
Requires-Dist: hy
Requires-Dist: pygls
Requires-Dist: jedhy
